<annotation>
	<folder>train</folder>
	<filename>pc24.jpg</filename>
	<path>C:\ObjectDetection\models\research\object_detection\image\train\pc24.jpg</path>
	<source>
		<database>Unknown</database>
	</source>
	<size>
		<width>480</width>
		<height>360</height>
		<depth>3</depth>
	</size>
	<segmented>0</segmented>
	<object>
		<name>pc</name>
		<pose>Unspecified</pose>
		<truncated>0</truncated>
		<difficult>0</difficult>
		<bndbox>
			<xmin>44</xmin>
			<ymin>97</ymin>
			<xmax>135</xmax>
			<ymax>178</ymax>
		</bndbox>
	</object>
	<object>
		<name>pc</name>
		<pose>Unspecified</pose>
		<truncated>0</truncated>
		<difficult>0</difficult>
		<bndbox>
			<xmin>141</xmin>
			<ymin>89</ymin>
			<xmax>224</xmax>
			<ymax>160</ymax>
		</bndbox>
	</object>
	<object>
		<name>pc</name>
		<pose>Unspecified</pose>
		<truncated>0</truncated>
		<difficult>0</difficult>
		<bndbox>
			<xmin>220</xmin>
			<ymin>82</ymin>
			<xmax>294</xmax>
			<ymax>161</ymax>
		</bndbox>
	</object>
	<object>
		<name>pc</name>
		<pose>Unspecified</pose>
		<truncated>0</truncated>
		<difficult>0</difficult>
		<bndbox>
			<xmin>298</xmin>
			<ymin>82</ymin>
			<xmax>375</xmax>
			<ymax>157</ymax>
		</bndbox>
	</object>
	<object>
		<name>manusia</name>
		<pose>Unspecified</pose>
		<truncated>0</truncated>
		<difficult>0</difficult>
		<bndbox>
			<xmin>273</xmin>
			<ymin>68</ymin>
			<xmax>471</xmax>
			<ymax>289</ymax>
		</bndbox>
	</object>
	<object>
		<name>kursi</name>
		<pose>Unspecified</pose>
		<truncated>0</truncated>
		<difficult>0</difficult>
		<bndbox>
			<xmin>277</xmin>
			<ymin>177</ymin>
			<xmax>447</xmax>
			<ymax>345</ymax>
		</bndbox>
	</object>
</annotation>
